{
    "instance_name": "Ari-C4-pB-d70-w100",
    "routes": [
        [1, 4, 3, 5],
        [2, 6, 7, 8, 9],
        [15, 16, 17, 18, 19, 20],
        [10, 11, 12, 13, 14]
    ],
    "cost": 1906.8125366724585,
    "metadata": {
        "source": "kayros 0.2.0.dev0 TD-ACO (seed=1010, time_limit=120.0s)",
        "validated_by": "mamut-routing-lib td Duration checker",
        "route_durations": [396.8047297297298, 612.1594446967977, 335.1433790740547, 562.704983171876],
        "route_departure_times": [31.413732651570495, 44.39216216216216, 766.0214285714286, 375.0],
        "authors": "Florian Rascoussier (0nyr)",
        "validated_cost": 1906.8125366724585,
        "validated_num_routes": 4,
        "date": "2026-07-06T05:07:47"
    },
    "objective_function": "Duration"
}
