{
    "instance_name": "Ari-B10-pB-d98-w0",
    "routes": [
        [21, 39, 27, 16, 19, 7],
        [17, 15, 12, 20, 28, 9, 37, 26, 18, 22, 13],
        [1, 5, 11, 4, 24],
        [29, 23, 6, 33, 31, 8, 10, 40, 35],
        [30, 38, 34, 36],
        [25, 3, 14, 2],
        [32]
    ],
    "cost": 1962.9054818300585,
    "metadata": {
        "source": "kayros 0.0.1.dev0 TD-ACO (seed=1618, time_limit=300.0s)",
        "validated_by": "mamut-routing-lib td Duration checker",
        "route_durations": [284.5472972972973, 374.3716678968885, 312.75200876552225, 344.5336255174093, 208.49588235294118, 294.325, 143.8800000000001],
        "route_departure_times": [0.0, 0.5557452305246331, 0.0, 0.0, 1038.594117647059, 0.0, 1065.0],
        "authors": "Florian Rascoussier (0nyr)",
        "validated_cost": 1962.9054818300585,
        "validated_num_routes": 7,
        "date": "2026-07-04T21:41:47"
    },
    "objective_function": "Duration"
}
