{
    "instance_name": "Ari-A4-pA-d98-w25",
    "instance_origin": "Ari2018",
    "benchmark_name": "Ari2018",
    "num_customers": 30,
    "num_vehicles": 30,
    "vehicle_capacity": 125,
    "coordinates": [
        [68.40345612349893, -8.579474792960658],
        [-6.930945963101726, 6.215220200923635],
        [13.101700421974684, 4.566567923488765],
        [-0.29522786990665684, -1.5950925079436926],
        [-0.986956389188443, 6.01084921538094],
        [-23.795531538698786, -8.135903384566333],
        [-2.8826751476333174, 6.303180115611722],
        [5.667586924039679, -0.3677518945743721],
        [0.8445508302259207, 6.552898336801695],
        [-2.3491344360143045, 2.15963274721304],
        [2.083049968334405, 0.4357704488255548],
        [-1.7456745673832903, -4.148703589339338],
        [3.7038369077895266, 16.653273287872857],
        [-14.351797315817333, 2.0389651382402305],
        [1.5928967999285175, -3.441149756298116],
        [-3.7351113861427736, -0.7831276841147283],
        [3.657212239153793, 2.800090402097666],
        [-6.583629541614302, -10.041548192806353],
        [-7.141442192886838, 0.8248893520735039],
        [-8.04672347676065, -6.039962707617357],
        [5.413545189718959, -3.3386180721783365],
        [-0.8429006497922132, 9.086110493397321],
        [-7.543197055959742, -14.22083299653695],
        [-11.751615825082984, -16.54569094533483],
        [-4.934997563336871, 2.995220597581816],
        [3.0539010304499734, 6.103694391228683],
        [10.523185917187524, -0.10957569869377866],
        [-8.269490890404297, 3.377059642599976],
        [-5.060810078621725, -3.612309189032335],
        [-0.358613707609212, 3.3527273120522345],
        [-0.43844675634644725, 1.4835918066075393]
    ],
    "demands": [0, 16, 2, 8, 1, 25, 45, 1, 2, 10, 1, 12, 21, 1, 72, 1, 1, 9, 9, 6, 9, 1, 10, 1, 104, 51, 41, 11, 26, 1, 21],
    "service_times": [0, 1, 14, 11, 7, 11, 13, 1, 11, 17, 9, 19, 26, 4, 12, 20, 1, 17, 9, 10, 19, 18, 11, 25, 23, 20, 17, 6, 25, 18, 11],
    "time_windows": [
        [0, 1700],
        [12, 128],
        [18, 151],
        [23, 172],
        [26, 183],
        [42, 246],
        [61, 322],
        [66, 343],
        [72, 365],
        [74, 376],
        [77, 386],
        [79, 395],
        [88, 431],
        [98, 469],
        [107, 508],
        [117, 545],
        [123, 570],
        [133, 612],
        [139, 635],
        [142, 646],
        [148, 669],
        [152, 686],
        [161, 721],
        [162, 728],
        [170, 757],
        [172, 767],
        [175, 779],
        [183, 810],
        [186, 822],
        [190, 838],
        [192, 848]
    ],
    "depot": 0,
    "horizon": [0.0, 1700.0],
    "td": {
        "model": "atf-ndcpwlf",
        "atf_path": "Ari-A4-pA-d98-w25.atf.json.gz",
        "atf_sha256": "614bc7cb06bf794ffcc1c5381f8b97c12fadb36573473dc6ca7974e91b94ab2b"
    },
    "metadata": {
        "authors": "Florian Rascoussier (0nyr)",
        "generated_at": "2026-07-03",
        "generator": {
            "name": "populate_td_ari_vu",
            "version": "1",
            "source": "Arigliano-generator raw trees + legacy TDVRPTW-benchmarks attribute harvest + option-A curated selection"
        },
        "raw_source": "Ari2018/30/Delta98/PatternA/Width_25/30Anodi_4_tw_new.txt",
        "legacy_attribute_source": "n=32/Ari4-n=32-fc2636e9f41b40d8c8df5b56f7ad8f126b703f8b.json",
        "parameters": {
            "delta": 98,
            "pattern": "A",
            "width": 25,
            "tw_class": "A",
            "index": 4
        },
        "coordinates_method": {
            "name": "stress-layout (deterministic SMACOF, classical-MDS init, 2D)",
            "stress1": 0.10604556206244284,
            "pearson_r": 0.989335313108717
        },
        "notes": "Origin: the Ari2018 TD-TSPTW benchmark (Arigliano-generator raw data; IGP model with 73 speed zones and 3 profiles), consolidated into exact arrival-time NDCPWLFs. This canonical family is the VRP variant curated by Onyr: demands, vehicle capacity, fleet size and service times were generated once by the legacy TDVRPTW-benchmarks pipeline and are pinned here verbatim; raw time windows are kept unchanged. The family ships a deterministic curated subset (one instance per structural cell, legacy-BKS candidates preferred, ties by ascending SHA-256 of the instance name); the full factorial raw trees remain available upstream. Coordinates are a deterministic stress-layout embedding of the raw distance matrix."
    }
}
